viggocore/__init__.py
viggocore/_version.py
viggocore/celery.py
viggocore/database.py
viggocore/queue.py
viggocore/request.py
viggocore/resources.py
viggocore/scheduler.py
viggocore/system.py
viggocore/bootstrap/__init__.py
viggocore/bootstrap/roles.py
viggocore/bootstrap/routes.py
viggocore/bootstrap/default/__init__.py
viggocore/bootstrap/default/application.py
viggocore/bootstrap/default/domain.py
viggocore/bootstrap/default/policies.py
viggocore/bootstrap/default/user.py
viggocore/common/__init__.py
viggocore/common/controller.py
viggocore/common/exception.py
viggocore/common/input.py
viggocore/common/manager.py
viggocore/common/operation_after_post.py
viggocore/common/utils.py
viggocore/common/valida_cpf_cnpj.py
viggocore/common/subsystem/__init__.py
viggocore/common/subsystem/apihandler.py
viggocore/common/subsystem/controller.py
viggocore/common/subsystem/driver.py
viggocore/common/subsystem/entity.py
viggocore/common/subsystem/manager.py
viggocore/common/subsystem/operation.py
viggocore/common/subsystem/pagination.py
viggocore/common/subsystem/router.py
viggocore/common/subsystem/transaction_manager.py
viggocore/common/subsystem/gerar_pdf/__init__.py
viggocore/common/subsystem/gerar_pdf/layout_padrao_html.py
viggocore/common/subsystem/gerar_pdf/relatorio_html.py
viggocore/common/subsystem/gerar_pdf/relatorio_utils.py
viggocore/common/subsystem/gerar_pdf/relatorio_styles/__init__.py
viggocore/common/subsystem/gerar_pdf/relatorio_styles/style_1.py
viggocore/common/subsystem/gerar_pdf/relatorio_styles/style_2.py
viggocore/common/subsystem/gerar_pdf/relatorio_styles/style_3.py
viggocore/common/subsystem/gerar_pdf/relatorio_styles/style_4.py
viggocore/common/subsystem/gerar_pdf/relatorio_styles/style_5.py
viggocore/common/subsystem/gerar_pdf/relatorio_styles/style_6.py
viggocore/common/subsystem/gerar_pdf/relatorio_styles/style_7.py
viggocore/common/subsystem/gerar_pdf/relatorio_styles/style_8.py
viggocore-1.7.13.dist-info/AUTHORS
viggocore-1.7.13.dist-info/LICENSE
viggocore-1.7.13.dist-info/METADATA
viggocore-1.7.13.dist-info/WHEEL
viggocore-1.7.13.dist-info/top_level.txt
viggocore-1.7.13.dist-info/RECORD
